task_manager/__init__.py
task_manager/api.py
task_manager/assumptions.py
task_manager/cli.py
task_manager/context_utils.py
task_manager/file_watcher.py
task_manager/importer.py
task_manager/install.py
task_manager/mcp_server.py
task_manager/models.py
task_manager/monitoring.py
task_manager/performance.py
task_manager/py.typed
task_manager/ra_instructions.py
task_manager/ra_tag_utils.py
task_manager/tools.py
task_manager/database/README.md
task_manager/database/REFACTORING_NOTES.md
task_manager/database/__init__.py
task_manager/database/_legacy.py
task_manager/database/connection.py
task_manager/database/knowledge.py
task_manager/database/locks.py
task_manager/database/projects.py
task_manager/database/sessions.py
task_manager/database/tasks.py
task_manager/routers/__init__.py
task_manager/routers/board.py
task_manager/routers/epics.py
task_manager/routers/health.py
task_manager/routers/knowledge.py
task_manager/routers/planning.py
task_manager/routers/projects.py
task_manager/routers/tasks.py
task_manager/static/index.html
task_manager/static/planning.html
task_manager/static/css/components.css
task_manager/static/css/forms-special.css
task_manager/static/css/header.css
task_manager/static/css/kanban.css
task_manager/static/css/main.css
task_manager/static/css/modals.css
task_manager/static/css/planning.css
task_manager/static/css/tabs-tables.css
task_manager/static/js/app.js
task_manager/static/js/assumption-insights-modal.js
task_manager/static/js/board.js
task_manager/static/js/drag-drop.js
task_manager/static/js/event-handlers.js
task_manager/static/js/filters.js
task_manager/static/js/knowledge-modal.js
task_manager/static/js/modal.js
task_manager/static/js/planning.js
task_manager/static/js/state.js
task_manager/static/js/utils.js
task_manager/static/js/websocket.js
task_manager/tools_lib/__init__.py
task_manager/tools_lib/assumptions.py
task_manager/tools_lib/base.py
task_manager/tools_lib/instructions.py
task_manager/tools_lib/knowledge.py
project_manager_mcp-0.2.1.dist-info/METADATA
project_manager_mcp-0.2.1.dist-info/WHEEL
project_manager_mcp-0.2.1.dist-info/entry_points.txt
project_manager_mcp-0.2.1.dist-info/licenses/LICENSE
project_manager_mcp-0.2.1.dist-info/RECORD
