Metadata-Version: 2.4
Name: project-manager-mcp
Version: 0.2.1
Summary: Project Manager MCP with SQLite database layer and atomic locking
Project-URL: Homepage, https://github.com/Commands-com/pm
Project-URL: Repository, https://github.com/Commands-com/pm
Project-URL: Documentation, https://github.com/Commands-com/pm#readme
Project-URL: Bug Tracker, https://github.com/Commands-com/pm/issues
Author: Project Manager MCP Contributors
Maintainer: Project Manager MCP Contributors
License: MIT
License-File: LICENSE
Keywords: asyncio,fastapi,mcp,model-context-protocol,project-management,sqlite
Classifier: Development Status :: 3 - Alpha
Classifier: Framework :: AsyncIO
Classifier: Framework :: FastAPI
Classifier: Intended Audience :: Developers
Classifier: License :: OSI Approved :: MIT License
Classifier: Programming Language :: Python :: 3
Classifier: Programming Language :: Python :: 3.9
Classifier: Programming Language :: Python :: 3.10
Classifier: Programming Language :: Python :: 3.11
Classifier: Programming Language :: Python :: 3.12
Classifier: Topic :: Database
Classifier: Topic :: Internet :: WWW/HTTP :: HTTP Servers
Classifier: Topic :: Software Development :: Libraries :: Python Modules
Requires-Python: >=3.9
Requires-Dist: aiohttp>=3.8.0
Requires-Dist: click>=8.0
Requires-Dist: fastapi>=0.100.0
Requires-Dist: fastmcp>=0.1.0
Requires-Dist: psutil>=5.9.0
Requires-Dist: pydantic>=2.0
Requires-Dist: pyyaml>=6.0
Requires-Dist: uvicorn[standard]>=0.20.0
Requires-Dist: watchdog>=3.0.0
Requires-Dist: websockets>=11.0
Provides-Extra: dev
Requires-Dist: httpx>=0.24; extra == 'dev'
Requires-Dist: playwright>=1.30.0; extra == 'dev'
Requires-Dist: pytest-asyncio>=0.21; extra == 'dev'
Requires-Dist: pytest-benchmark>=4.0; extra == 'dev'
Requires-Dist: pytest-cov>=4.0; extra == 'dev'
Requires-Dist: pytest-html>=3.0; extra == 'dev'
Requires-Dist: pytest-xdist>=3.0; extra == 'dev'
Requires-Dist: pytest>=7.0; extra == 'dev'
Requires-Dist: requests>=2.31.0; extra == 'dev'
Requires-Dist: selenium>=4.0; extra == 'dev'
Requires-Dist: websockets>=11.0; extra == 'dev'
Provides-Extra: lint
Requires-Dist: black>=23.0; extra == 'lint'
Requires-Dist: mypy>=1.0; extra == 'lint'
Requires-Dist: ruff>=0.1.0; extra == 'lint'
Requires-Dist: types-pyyaml; extra == 'lint'
Provides-Extra: test
Requires-Dist: httpx>=0.24; extra == 'test'
Requires-Dist: playwright>=1.30.0; extra == 'test'
Requires-Dist: pytest-asyncio>=0.21; extra == 'test'
Requires-Dist: pytest>=7.0; extra == 'test'
Requires-Dist: requests>=2.31.0; extra == 'test'
Requires-Dist: selenium>=4.0; extra == 'test'
Requires-Dist: websockets>=11.0; extra == 'test'
